surfpack/Convolver.py
surfpack/Functional.py
surfpack/WeightFunction.py
surfpack/__init__.py
surfpack/external_potential.py
surfpack/grid.py
surfpack/hardsphere.py
surfpack/pcsaft.py
surfpack/profile.py
surfpack/saft.py
surfpack/saft_hardsphere.py
surfpack/saftvrmie.py
surfpack/saftvrqmie.py
surfpack/saftvrsigma.py
surfpack/solvers.py
surfpack-1.0.0.dist-info/LICENSE
surfpack-1.0.0.dist-info/METADATA
surfpack-1.0.0.dist-info/WHEEL
surfpack-1.0.0.dist-info/top_level.txt
surfpack-1.0.0.dist-info/RECORD
