Metadata-Version: 2.1
Name: surfpack
Version: 1.0.0
Summary: Density Functional Theory for surfaces and interfaces
Home-page: https://github.com/thermotools/surfpack
Author: Vegard Gjeldvik Jervell
Author-email: Vegard Gjeldvik Jervell <vegard.g.jervell@ntnu.no>, Morten Hammer <morten.hammer@ntnu.no>
Maintainer-email: Vegard Gjeldvik Jervell <vegard.g.jervell@ntnu.no>, Morten Hammer <morten.hammer@ntnu.no>
Project-URL: Homepage, https://thermotools.github.io/surfpack
Project-URL: Bug Tracker, https://github.com/thermotools/surfpack/issues
Keywords: physics,thermodynamics,equations_of_state,phase_equilibria,SAFT,DFT,density_functional_theory
Classifier: Programming Language :: Python :: 3
Classifier: Programming Language :: Fortran
Classifier: Operating System :: MacOS
Classifier: Operating System :: POSIX :: Linux
Classifier: Operating System :: Microsoft :: Windows
Classifier: License :: OSI Approved :: MIT License
Requires-Python: >=3.9
License-File: LICENSE
